{
  "mode": "pre",
  "tag": "pre",
  "initialVersions": {
    "create-remix": "1.16.0",
    "remix": "1.16.0",
    "@remix-run/architect": "1.16.0",
    "@remix-run/cloudflare": "1.16.0",
    "@remix-run/cloudflare-pages": "1.16.0",
    "@remix-run/cloudflare-workers": "1.16.0",
    "@remix-run/css-bundle": "1.16.0",
    "@remix-run/deno": "1.16.0",
    "@remix-run/dev": "1.16.0",
    "@remix-run/eslint-config": "1.16.0",
    "@remix-run/express": "1.16.0",
    "@remix-run/netlify": "1.16.0",
    "@remix-run/node": "1.16.0",
    "@remix-run/react": "1.16.0",
    "@remix-run/serve": "1.16.0",
    "@remix-run/server-runtime": "1.16.0",
    "@remix-run/testing": "1.16.0",
    "@remix-run/vercel": "1.16.0"
  },
  "changesets": [
    "afraid-coats-count",
    "better-opt-out-of-revalidations",
    "big-carrots-attend",
    "calm-falcons-boil",
    "eslint-no-display-name",
    "export-use-match",
    "five-poems-stare",
    "good-laws-marry",
    "include-css-bundle-in-manifest-hash",
    "light-bikes-exercise",
    "polite-garlics-invite",
    "poor-nails-warn",
    "slimy-snakes-do",
    "tsconfig-no-modify",
    "twenty-toys-laugh",
    "update-babel",
    "v2-meta-loader-data-type",
    "young-dingos-sleep"
  ]
}
